odoo/addons/product_template_copy_attributes/README.rst
odoo/addons/product_template_copy_attributes/__init__.py
odoo/addons/product_template_copy_attributes/__manifest__.py
odoo/addons/product_template_copy_attributes/i18n/it.po
odoo/addons/product_template_copy_attributes/i18n/product_template_copy_attributes.pot
odoo/addons/product_template_copy_attributes/models/__init__.py
odoo/addons/product_template_copy_attributes/models/product_template.py
odoo/addons/product_template_copy_attributes/readme/CONTRIBUTORS.rst
odoo/addons/product_template_copy_attributes/readme/DESCRIPTION.rst
odoo/addons/product_template_copy_attributes/readme/ROADMAP.rst
odoo/addons/product_template_copy_attributes/static/description/icon.png
odoo/addons/product_template_copy_attributes/static/description/index.html
odoo/addons/product_template_copy_attributes/tests/__init__.py
odoo/addons/product_template_copy_attributes/tests/test_product_template_copy_attributes.py
odoo12_addon_product_template_copy_attributes-12.0.1.0.0.99.dev6.dist-info/METADATA
odoo12_addon_product_template_copy_attributes-12.0.1.0.0.99.dev6.dist-info/WHEEL
odoo12_addon_product_template_copy_attributes-12.0.1.0.0.99.dev6.dist-info/top_level.txt
odoo12_addon_product_template_copy_attributes-12.0.1.0.0.99.dev6.dist-info/RECORD
